AUTHORS
LICENSE
MANIFEST.in
README
README.md
setup.py
salad/__init__.py
salad/cli.py
salad/logger.py
salad.egg-info/PKG-INFO
salad.egg-info/SOURCES.txt
salad.egg-info/dependency_links.txt
salad.egg-info/entry_points.txt
salad.egg-info/not-zip-safe
salad.egg-info/requires.txt
salad.egg-info/top_level.txt
salad/features/salad_steps.py
salad/features/salad_terrains.py
salad/features/steps-browser-browsers.feature
salad/features/steps-browser-drag.feature
salad/features/steps-browser-elements.feature
salad/features/steps-browser-forms.feature
salad/features/steps-browser-javascript.feature
salad/features/steps-browser-mouse.feature
salad/features/steps-browser-navigation.feature
salad/features/steps-browser-page.feature
salad/steps/__init__.py
salad/steps/common.py
salad/steps/djangoify.py
salad/steps/everything.py
salad/steps/browser/__init__.py
salad/steps/browser/alerts.py
salad/steps/browser/browsers.py
salad/steps/browser/elements.py
salad/steps/browser/finders.py
salad/steps/browser/forms.py
salad/steps/browser/javascript.py
salad/steps/browser/mouse.py
salad/steps/browser/navigation.py
salad/steps/browser/page.py
salad/terrains/__init__.py
salad/terrains/browser.py
salad/terrains/chrome.py
salad/terrains/common.py
salad/terrains/djangoify.py
salad/terrains/everything.py
salad/terrains/firefox.py
salad/terrains/zope.py
salad/tests/__init__.py
salad/tests/util.py
salad/tests/html/browser/1.html
salad/tests/html/browser/2.html
salad/tests/html/browser/3.html
salad/tests/html/browser/basic.html
salad/tests/html/browser/elements.html
salad/tests/html/browser/form.html
salad/tests/html/browser/iframe.html
salad/tests/html/browser/iframe_inner.html
salad/tests/html/browser/js.html
salad/tests/html/browser/mouse.html
salad/tests/html/browser/page.html