Metadata-Version: 1.1
Name: salad
Version: 0.4.13
Summary: A nice mix of great BDD ingredients
Home-page: https://github.com/wieden-kennedy/salad
Author: Steven Skoczen
Author-email: steven.skoczen@wk.com
License: UNKNOWN
Platform: UNKNOWN
Classifier: Programming Language :: Python
Classifier: License :: OSI Approved :: BSD License
Classifier: Operating System :: OS Independent
Classifier: Development Status :: 4 - Beta
Classifier: Environment :: Web Environment
Classifier: Intended Audience :: Developers
Classifier: Topic :: Internet :: WWW/HTTP
Classifier: Topic :: Software Development :: Libraries :: Python Modules
